kbtogglr/__init__.py
kbtogglr/__main__.py
kbtogglr/images/off.png
kbtogglr/images/on.png
kbtogglr-1.1.1.data/data/share/applications/org.kbtogglr.desktop
kbtogglr-1.1.1.dist-info/LICENSE
kbtogglr-1.1.1.dist-info/METADATA
kbtogglr-1.1.1.dist-info/WHEEL
kbtogglr-1.1.1.dist-info/entry_points.txt
kbtogglr-1.1.1.dist-info/top_level.txt
kbtogglr-1.1.1.dist-info/RECORD
