Metadata-Version: 2.1
Name: kbtogglr
Version: 1.1.1
Summary: Toggle keyboard on and off for xinput
Home-page: https://github.com/jshwi/kbtogglr
Author: Stephen Whitlock
Author-email: stephen@jshwisolutions.com
License: MIT
Keywords: keyboard,xorg,xserver,xinput
Platform: GNU/Linux
Classifier: Programming Language :: Python :: 3.8
Classifier: License :: OSI Approved :: MIT License
Classifier: Operating System :: POSIX :: Linux
Requires-Python: >=3.8
License-File: LICENSE
Requires-Dist: appdirs (<=2.0.0,>=1.0.0)
